mat2py/__init__.py
mat2py/common/__init__.py
mat2py/common/backends.py
mat2py/common/logger.py
mat2py/common/utils.py
mat2py/config.py
mat2py/core/__init__.py
mat2py/core/_internal/__init__.py
mat2py/core/_internal/array.py
mat2py/core/_internal/cell.py
mat2py/core/_internal/helper.py
mat2py/core/_internal/math_helper.py
mat2py/core/_internal/object_handles.py
mat2py/core/_internal/struct.py
mat2py/core/apps.py
mat2py/core/audiovideo.py
mat2py/core/codetools.py
mat2py/core/datafun.py
mat2py/core/datamanager.py
mat2py/core/datastoreio.py
mat2py/core/datatypes.py
mat2py/core/elfun.py
mat2py/core/elmat.py
mat2py/core/funfun.py
mat2py/core/general.py
mat2py/core/graph2d.py
mat2py/core/graph3d.py
mat2py/core/graphics.py
mat2py/core/guide.py
mat2py/core/hds.py
mat2py/core/helptools.py
mat2py/core/images.py
mat2py/core/imagesci.py
mat2py/core/iofun.py
mat2py/core/lang.py
mat2py/core/mapreduceio.py
mat2py/core/matfun.py
mat2py/core/networklib.py
mat2py/core/ops.py
mat2py/core/optimfun.py
mat2py/core/plottools.py
mat2py/core/polyfun.py
mat2py/core/randfun.py
mat2py/core/scribe.py
mat2py/core/sparfun.py
mat2py/core/specfun.py
mat2py/core/specgraph.py
mat2py/core/strfun.py
mat2py/core/testframework.py
mat2py/core/timefun.py
mat2py/core/timeseries.py
mat2py/core/toolbox_packaging.py
mat2py/core/uitools.py
mat2py/core/verctrl.py
mat2py/core/webcam.py
mat2py/core/winfun.py
mat2py/toolbox/matlab/elmat/__init__.py
mat2py/toolbox/matlab/elmat/linspace.py
mat2py/toolbox/matlab/polyfun/__init__.py
mat2py/toolbox/matlab/polyfun/inpolygon.py
mat2py/toolbox/signal/signal/__init__.py
mat2py/toolbox/signal/signal/sinc.py
mat2py/version.py
mat2py-0.0.22.dist-info/LICENSE
mat2py-0.0.22.dist-info/METADATA
mat2py-0.0.22.dist-info/WHEEL
mat2py-0.0.22.dist-info/RECORD
