Metadata-Version: 2.1
Name: mat2py
Version: 0.0.22
Summary: mat2py mean to be drop-in replacement of Matlab by wrapping Numpy/Scipy/... packages.
Home-page: https://mat2py.org
License: MIT
Keywords: Matlab,Python,Numpy,Scipy
Author: mat2py
Author-email: chaoqingwang.nick@gmail.com
Requires-Python: >=3.7,<4
Classifier: Development Status :: 3 - Alpha
Classifier: Intended Audience :: Developers
Classifier: License :: OSI Approved :: MIT License
Classifier: Operating System :: OS Independent
Classifier: Programming Language :: Python :: 3
Classifier: Programming Language :: Python :: 3.7
Classifier: Programming Language :: Python :: 3.8
Classifier: Programming Language :: Python :: 3.9
Classifier: Programming Language :: Python :: 3.10
Classifier: Programming Language :: Python :: 3.11
Classifier: Topic :: Software Development :: Libraries :: Python Modules
Requires-Dist: executing (>=0.8.3,<0.9.0)
Requires-Dist: importlib_metadata (>=4.5.0,<5.0.0) ; python_version < "3.8"
Requires-Dist: numpy (>=1.21,<1.22) ; python_version < "3.8"
Requires-Dist: numpy (>=1.22.0,<2.0.0) ; python_version >= "3.8"
Requires-Dist: scipy (>=1.7,<1.8) ; python_version < "3.8"
Requires-Dist: scipy (>=1.7.0,<2.0.0) ; python_version >= "3.8"
Project-URL: Repository, https://github.com/mat2py/mat2py
